pkbrokers-0.1.20260108.61.data/purelib/pkbrokers/Disclaimer.txt
pkbrokers-0.1.20260108.61.data/purelib/pkbrokers/LICENSE.txt
pkbrokers-0.1.20260108.61.data/purelib/pkbrokers/README.txt
pkbrokers-0.1.20260108.61.data/purelib/pkbrokers/__init__.py
pkbrokers-0.1.20260108.61.data/purelib/pkbrokers/envupdater.py
pkbrokers-0.1.20260108.61.data/purelib/pkbrokers/requirements.txt
pkbrokers-0.1.20260108.61.data/purelib/pkbrokers/bot/__init__.py
pkbrokers-0.1.20260108.61.data/purelib/pkbrokers/bot/consumer.py
pkbrokers-0.1.20260108.61.data/purelib/pkbrokers/bot/dataSharingManager.py
pkbrokers-0.1.20260108.61.data/purelib/pkbrokers/bot/orchestrator.py
pkbrokers-0.1.20260108.61.data/purelib/pkbrokers/bot/tickbot.py
pkbrokers-0.1.20260108.61.data/purelib/pkbrokers/kite/__init__.py
pkbrokers-0.1.20260108.61.data/purelib/pkbrokers/kite/authenticator.py
pkbrokers-0.1.20260108.61.data/purelib/pkbrokers/kite/candleAggregator.py
pkbrokers-0.1.20260108.61.data/purelib/pkbrokers/kite/databasewriter.py
pkbrokers-0.1.20260108.61.data/purelib/pkbrokers/kite/datamanager.py
pkbrokers-0.1.20260108.61.data/purelib/pkbrokers/kite/inMemoryCandleStore.py
pkbrokers-0.1.20260108.61.data/purelib/pkbrokers/kite/instrumentHistory.py
pkbrokers-0.1.20260108.61.data/purelib/pkbrokers/kite/instruments.py
pkbrokers-0.1.20260108.61.data/purelib/pkbrokers/kite/kiteTokenWatcher.py
pkbrokers-0.1.20260108.61.data/purelib/pkbrokers/kite/localCandleDatabase.py
pkbrokers-0.1.20260108.61.data/purelib/pkbrokers/kite/threadSafeDatabase.py
pkbrokers-0.1.20260108.61.data/purelib/pkbrokers/kite/tickMonitor.py
pkbrokers-0.1.20260108.61.data/purelib/pkbrokers/kite/tickProcessor.py
pkbrokers-0.1.20260108.61.data/purelib/pkbrokers/kite/ticks.py
pkbrokers-0.1.20260108.61.data/purelib/pkbrokers/kite/trader.py
pkbrokers-0.1.20260108.61.data/purelib/pkbrokers/kite/zerodhaWebSocketClient.py
pkbrokers-0.1.20260108.61.data/purelib/pkbrokers/kite/zerodhaWebSocketParser.py
pkbrokers-0.1.20260108.61.dist-info/licenses/LICENSE
pkbrokers-0.1.20260108.61.dist-info/METADATA
pkbrokers-0.1.20260108.61.dist-info/WHEEL
pkbrokers-0.1.20260108.61.dist-info/entry_points.txt
pkbrokers-0.1.20260108.61.dist-info/top_level.txt
pkbrokers-0.1.20260108.61.dist-info/RECORD
