Metadata-Version: 2.4
Name: pkbrokers
Version: 0.1.20260108.61
Summary: A Python-based stock broker module
Home-page: https://github.com/pkjmesra/pkbrokers
Download-URL: https://github.com/pkjmesra/pkbrokers/archive/v0.1.20260108.61.zip
Author: pkjmesra
Author-email: pkjmesra@gmail.com
License: OSI Approved (MIT)
Keywords: NSE,Technical Indicators,Scanning,Stock Scanners
Classifier: License :: OSI Approved :: MIT License
Classifier: Operating System :: Microsoft :: Windows
Classifier: Operating System :: MacOS
Classifier: Operating System :: POSIX :: Linux
Classifier: Programming Language :: Python :: 3
Classifier: Programming Language :: Python :: 3.12
License-File: LICENSE
Requires-Dist: gitpython
Requires-Dist: numpy==1.26.4
Requires-Dist: pandas==2.2.3
Requires-Dist: PKDevTools>=0.13.20260108.322
Requires-Dist: PKNSETools>=0.1.20260108.149
Requires-Dist: pygithub
Requires-Dist: pyotp
Requires-Dist: python-telegram-bot[all]<20.0,>=13.4
Requires-Dist: pytz
Requires-Dist: telethon
Requires-Dist: urllib3
Requires-Dist: kiteconnect==5.0.1
Requires-Dist: websockets<11.0,>=10.4
Dynamic: author
Dynamic: author-email
Dynamic: classifier
Dynamic: description
Dynamic: description-content-type
Dynamic: download-url
Dynamic: home-page
Dynamic: keywords
Dynamic: license
Dynamic: license-file
Dynamic: requires-dist
Dynamic: summary
